README.rst
setup.py
sqlalchemy_pgcatalog/__init__.py
sqlalchemy_pgcatalog.egg-info/PKG-INFO
sqlalchemy_pgcatalog.egg-info/SOURCES.txt
sqlalchemy_pgcatalog.egg-info/dependency_links.txt
sqlalchemy_pgcatalog.egg-info/requires.txt
sqlalchemy_pgcatalog.egg-info/top_level.txt