Metadata-Version: 1.1
Name: sqlalchemy-pgcatalog
Version: 0.1.0
Summary: SQLAlchemy definitions for PostgreSQL catalog tables
Home-page: https://github.com/renshawbay/sqlalchemy_pgcatalog
Author: Renshaw Bay
Author-email: technology@renshawbay.com
License: UNKNOWN
Platform: UNKNOWN
Classifier: Topic :: Database
Classifier: License :: OSI Approved :: MIT License
Classifier: Programming Language :: Python :: 3.2
Classifier: Programming Language :: Python :: 3.3
Classifier: Programming Language :: Python :: 3.4
